airavata_mft_sdk/CredCommon_pb2.py
airavata_mft_sdk/CredCommon_pb2_grpc.py
airavata_mft_sdk/MFTAgentStubs_pb2.py
airavata_mft_sdk/MFTAgentStubs_pb2_grpc.py
airavata_mft_sdk/MFTTransferApi_pb2.py
airavata_mft_sdk/MFTTransferApi_pb2_grpc.py
airavata_mft_sdk/__init__.py
airavata_mft_sdk/mft_client.py
airavata_mft_sdk/azure/AzureCredential_pb2.py
airavata_mft_sdk/azure/AzureCredential_pb2_grpc.py
airavata_mft_sdk/azure/AzureSecretService_pb2.py
airavata_mft_sdk/azure/AzureSecretService_pb2_grpc.py
airavata_mft_sdk/azure/AzureStorageService_pb2.py
airavata_mft_sdk/azure/AzureStorageService_pb2_grpc.py
airavata_mft_sdk/azure/AzureStorage_pb2.py
airavata_mft_sdk/azure/AzureStorage_pb2_grpc.py
airavata_mft_sdk/azure/__init__.py
airavata_mft_sdk/box/BoxCredential_pb2.py
airavata_mft_sdk/box/BoxCredential_pb2_grpc.py
airavata_mft_sdk/box/BoxSecretService_pb2.py
airavata_mft_sdk/box/BoxSecretService_pb2_grpc.py
airavata_mft_sdk/box/BoxStorageService_pb2.py
airavata_mft_sdk/box/BoxStorageService_pb2_grpc.py
airavata_mft_sdk/box/BoxStorage_pb2.py
airavata_mft_sdk/box/BoxStorage_pb2_grpc.py
airavata_mft_sdk/box/__init__.py
airavata_mft_sdk/common/StorageCommon_pb2.py
airavata_mft_sdk/common/StorageCommon_pb2_grpc.py
airavata_mft_sdk/common/__init__.py
airavata_mft_sdk/dropbox/DropboxCredential_pb2.py
airavata_mft_sdk/dropbox/DropboxCredential_pb2_grpc.py
airavata_mft_sdk/dropbox/DropboxSecretService_pb2.py
airavata_mft_sdk/dropbox/DropboxSecretService_pb2_grpc.py
airavata_mft_sdk/dropbox/DropboxStorageService_pb2.py
airavata_mft_sdk/dropbox/DropboxStorageService_pb2_grpc.py
airavata_mft_sdk/dropbox/DropboxStorage_pb2.py
airavata_mft_sdk/dropbox/DropboxStorage_pb2_grpc.py
airavata_mft_sdk/dropbox/__init__.py
airavata_mft_sdk/ftp/FTPCredential_pb2.py
airavata_mft_sdk/ftp/FTPCredential_pb2_grpc.py
airavata_mft_sdk/ftp/FTPSecretService_pb2.py
airavata_mft_sdk/ftp/FTPSecretService_pb2_grpc.py
airavata_mft_sdk/ftp/FTPStorageService_pb2.py
airavata_mft_sdk-0.0.1a34.dist-info/LICENSE
airavata_mft_sdk-0.0.1a34.dist-info/METADATA
airavata_mft_sdk-0.0.1a34.dist-info/WHEEL
airavata_mft_sdk-0.0.1a34.dist-info/top_level.txt
airavata_mft_sdk-0.0.1a34.dist-info/RECORD
