Metadata-Version: 2.1
Name: airavata-mft-sdk
Version: 0.0.1a34
Summary: Python SDK for Apache Airavata Managed File Transfers (MFT)
Home-page: https://github.com/apache/airavata-mft
Author: Airavata MFT Developers
Author-email: dev@airavata.apache.org
Project-URL: Bug Tracker, https://github.com/apache/airavata-mft/issues
Classifier: Programming Language :: Python :: 3
Classifier: License :: OSI Approved :: Apache Software License
Classifier: Operating System :: OS Independent
Requires-Python: >=3.6
License-File: LICENSE
Requires-Dist: grpcio >=1.44.0
Requires-Dist: grpcio-tools >=1.44.0
Requires-Dist: google-api-python-client >=2.0.0
